mc_providers/__init__.py
mc_providers/cache.py
mc_providers/errors.py
mc_providers/exceptions.py
mc_providers/mediacloud.py
mc_providers/onlinenews.py
mc_providers/provider.py
mc_providers/reddit.py
mc_providers/twitter.py
mc_providers/youtube.py
mc_providers/language/__init__.py
mc_providers/language/ca_stop_words.txt
mc_providers/language/da_stop_words.txt
mc_providers/language/de_stop_words.txt
mc_providers/language/en_stop_words.txt
mc_providers/language/es_stop_words.txt
mc_providers/language/fi_stop_words.txt
mc_providers/language/fr_stop_words.txt
mc_providers/language/ha_stop_words.txt
mc_providers/language/hi_stop_words.txt
mc_providers/language/hu_stop_words.txt
mc_providers/language/it_stop_words.txt
mc_providers/language/ja_stop_words.txt
mc_providers/language/lt_stop_words.txt
mc_providers/language/nl_stop_words.txt
mc_providers/language/no_stop_words.txt
mc_providers/language/pt_stop_words.txt
mc_providers/language/ro_stop_words.txt
mc_providers/language/ru_stop_words.txt
mc_providers/language/sv_stop_words.txt
mc_providers/language/tr_stop_words.txt
mc_providers/language/zh_stop_words.txt
mc_providers/test/__init__.py
mc_providers/test/test_cache.py
mc_providers/test/test_module.py
mc_providers/test/test_onlinenews.py
mc_providers/test/test_onlinenews_errors.py
mc_providers/test/test_reddit.py
mc_providers/test/test_twitter.py
mc_providers/test/test_youtube.py
mc_providers-3.1.3.dist-info/WHEEL
mc_providers-3.1.3.dist-info/METADATA
mc_providers-3.1.3.dist-info/RECORD
