Metadata-Version: 2.1
Name: mc-providers
Version: 3.1.3
Summary: Search Providers package for Mediacloud
Author-email: Paige Gulley <nano3.14@gmail.com>, Rahul Bhargava <r.bhargava@northeastern.edu>
Requires-Python: >=3.8
Classifier: Development Status :: 3 - Alpha
Classifier: License :: OSI Approved :: MIT License
Classifier: Natural Language :: English
Classifier: Operating System :: OS Independent
Classifier: Programming Language :: Python
Classifier: Programming Language :: Python :: 3.8
Classifier: Programming Language :: Python :: 3.9
Requires-Dist: python-dateutil == 2.*
Requires-Dist: ciso8601==2.2.*
Requires-Dist: dateparser
Requires-Dist: requests
Requires-Dist: wayback-news-search == 1.*
Requires-Dist: fasttext == 0.9.*
Requires-Dist: mediacloud-metadata >= 1.0.0
Requires-Dist: mediacloud == 4.*
Requires-Dist: elasticsearch == 8.17.*
Requires-Dist: elasticsearch-dsl == 8.17.*
Requires-Dist: sigfig == 1.1.*
Requires-Dist: spacy == 3.8.*
Requires-Dist: statsd_client == 1.0.*
Requires-Dist: pre-commit ; extra == "dev"
Requires-Dist: python-dotenv ; extra == "dev"
Requires-Dist: pytest ; extra == "dev"
Requires-Dist: types-dateparser ~=1.2.0.20250208 ; extra == "pre-commit"
Requires-Dist: types-requests ~=2.32.0.20241016 ; extra == "pre-commit"
Provides-Extra: dev
Provides-Extra: pre-commit
